MANIFEST.in
README.rst
setup.cfg
setup.py
Flask_CacheBuster.egg-info/PKG-INFO
Flask_CacheBuster.egg-info/SOURCES.txt
Flask_CacheBuster.egg-info/dependency_links.txt
Flask_CacheBuster.egg-info/requires.txt
Flask_CacheBuster.egg-info/top_level.txt
flask_cachebuster/__init__.py