Metadata-Version: 1.1
Name: Flask-CacheBuster
Version: 1.0.0
Summary: Flask-CacheBuster is a lightweight Flask extension that adds a hash to the URL query parameters of each static file.
Home-page: https://github.com/israel-fl/Flask-CacheBuster
Author: Israel Flores
Author-email: jobs@israelfl.com
License: MIT
Platform: UNKNOWN
Classifier: Intended Audience :: Developers
Classifier: License :: OSI Approved :: MIT License
Classifier: Operating System :: OS Independent
Classifier: Programming Language :: Python
Classifier: Programming Language :: Python :: 3
Classifier: Topic :: Internet :: WWW/HTTP
Classifier: Topic :: Software Development :: Libraries :: Python Modules
Classifier: Topic :: System :: Logging
